warc2summary/faster_warc.py
warc2summary/heuristics.py
warc2summary/pipeline.py
warc2summary/warc_processor.py
warc2summary-0.0.12.dist-info/entry_points.txt
warc2summary-0.0.12.dist-info/LICENSE
warc2summary-0.0.12.dist-info/METADATA
warc2summary-0.0.12.dist-info/WHEEL
warc2summary-0.0.12.dist-info/RECORD
