Metadata-Version: 2.1
Name: warc2summary
Version: 0.0.12
Summary: warc2summary
Home-page: https://github.com/masamune-prog/warc2summary
License: MIT
Author: masamune-prog
Author-email: zgoh033@e.ntu.edu.sg
Requires-Python: >=3.9,<4.0
Classifier: Development Status :: 1 - Planning
Classifier: License :: OSI Approved :: MIT License
Classifier: Programming Language :: Python :: 3
Classifier: Programming Language :: Python :: 3.9
Classifier: Programming Language :: Python :: 3.10
Classifier: Programming Language :: Python :: 3.11
Classifier: Programming Language :: Python :: 3.12
Requires-Dist: bs4 (>=0.0.2,<0.0.3)
Requires-Dist: click (>=8.0.1)
Requires-Dist: fastwarc (>=0.14.7,<0.15.0)
Requires-Dist: instructor (>=1.3.5,<2.0.0) ; python_version >= "3.9" and python_version < "4.0"
Requires-Dist: lxml (>=5.2.2,<6.0.0)
Requires-Dist: pandas (>=2.2.2,<3.0.0) ; python_version >= "3.9" and python_version < "4.0"
Requires-Dist: tldextract (>=5.1.2,<6.0.0) ; python_version >= "3.8" and python_version < "4.0"
Requires-Dist: warcio (>=1.7.4,<2.0.0)
Project-URL: Changelog, https://github.com/masamune-prog/warc2summary/releases
Project-URL: Documentation, https://warc2summary.readthedocs.io
Project-URL: Repository, https://github.com/masamune-prog/warc2summary
